{
  "dllExports": [],
  "libExports": [
    {
      "name": "_CimAddFsToMergedImage@8"
    },
    {
      "name": "_CimCloseImage@4"
    },
    {
      "name": "_CimCloseStream@4"
    },
    {
      "name": "_CimCommitImage@4"
    },
    {
      "name": "_CimCreateAlternateStream@20"
    },
    {
      "name": "_CimCreateFile@16"
    },
    {
      "name": "_CimCreateHardLink@12"
    },
    {
      "name": "_CimCreateImage@16"
    },
    {
      "name": "_CimCreateMergedFile@20"
    },
    {
      "name": "_CimDeletePath@8"
    },
    {
      "name": "_CimDismountImage@4"
    },
    {
      "name": "_CimLookupFile@12"
    },
    {
      "name": "_CimMergeMountImage@16"
    },
    {
      "name": "_CimMountImage@16"
    },
    {
      "name": "_CimWriteStream@12"
    }
  ],
  "libPublicSymbols": [
    {
      "offset": 1958,
      "name": "__IMPORT_DESCRIPTOR_CIMFS"
    },
    {
      "offset": 2504,
      "name": "__NULL_IMPORT_DESCRIPTOR"
    },
    {
      "offset": 2812,
      "name": "CIMFS_NULL_THUNK_DATA"
    },
    {
      "offset": 3262,
      "name": "_CimCloseImage@4"
    },
    {
      "offset": 3262,
      "name": "__imp__CimCloseImage@4"
    },
    {
      "offset": 3370,
      "name": "_CimCloseStream@4"
    },
    {
      "offset": 3370,
      "name": "__imp__CimCloseStream@4"
    },
    {
      "offset": 3478,
      "name": "_CimCommitImage@4"
    },
    {
      "offset": 3478,
      "name": "__imp__CimCommitImage@4"
    },
    {
      "offset": 3586,
      "name": "_CimCreateAlternateStream@20"
    },
    {
      "offset": 3586,
      "name": "__imp__CimCreateAlternateStream@20"
    },
    {
      "offset": 3706,
      "name": "_CimCreateFile@16"
    },
    {
      "offset": 3706,
      "name": "__imp__CimCreateFile@16"
    },
    {
      "offset": 3814,
      "name": "_CimCreateHardLink@12"
    },
    {
      "offset": 3814,
      "name": "__imp__CimCreateHardLink@12"
    },
    {
      "offset": 3926,
      "name": "_CimCreateImage@16"
    },
    {
      "offset": 3926,
      "name": "__imp__CimCreateImage@16"
    },
    {
      "offset": 4150,
      "name": "_CimDeletePath@8"
    },
    {
      "offset": 4150,
      "name": "__imp__CimDeletePath@8"
    },
    {
      "offset": 4258,
      "name": "_CimDismountImage@4"
    },
    {
      "offset": 4258,
      "name": "__imp__CimDismountImage@4"
    },
    {
      "offset": 4590,
      "name": "_CimMountImage@16"
    },
    {
      "offset": 4590,
      "name": "__imp__CimMountImage@16"
    },
    {
      "offset": 4698,
      "name": "_CimWriteStream@12"
    },
    {
      "offset": 4698,
      "name": "__imp__CimWriteStream@12"
    },
    {
      "offset": 3146,
      "name": "_CimAddFsToMergedImage@8"
    },
    {
      "offset": 3146,
      "name": "__imp__CimAddFsToMergedImage@8"
    },
    {
      "offset": 4036,
      "name": "_CimCreateMergedFile@20"
    },
    {
      "offset": 4036,
      "name": "__imp__CimCreateMergedFile@20"
    },
    {
      "offset": 4368,
      "name": "_CimLookupFile@12"
    },
    {
      "offset": 4368,
      "name": "__imp__CimLookupFile@12"
    },
    {
      "offset": 4476,
      "name": "_CimMergeMountImage@16"
    },
    {
      "offset": 4476,
      "name": "__imp__CimMergeMountImage@16"
    }
  ],
  "libSymbols": [
    {
      "offset": 3146,
      "version": 0,
      "machine": 332,
      "timeDateStamp": 4084963498,
      "sizeOfData": 35,
      "dllName": "CIMFS.dll",
      "symbolName": "_CimAddFsToMergedImage@8",
      "type": "code",
      "nameType": "undecorate",
      "hint": 0,
      "name": "CimAddFsToMergedImage"
    },
    {
      "offset": 3262,
      "version": 0,
      "machine": 332,
      "timeDateStamp": 3966090606,
      "sizeOfData": 27,
      "dllName": "CIMFS.dll",
      "symbolName": "_CimCloseImage@4",
      "type": "code",
      "nameType": "undecorate",
      "hint": 1,
      "name": "CimCloseImage"
    },
    {
      "offset": 3370,
      "version": 0,
      "machine": 332,
      "timeDateStamp": 3689779345,
      "sizeOfData": 28,
      "dllName": "CIMFS.dll",
      "symbolName": "_CimCloseStream@4",
      "type": "code",
      "nameType": "undecorate",
      "hint": 2,
      "name": "CimCloseStream"
    },
    {
      "offset": 3478,
      "version": 0,
      "machine": 332,
      "timeDateStamp": 3227314218,
      "sizeOfData": 28,
      "dllName": "CIMFS.dll",
      "symbolName": "_CimCommitImage@4",
      "type": "code",
      "nameType": "undecorate",
      "hint": 3,
      "name": "CimCommitImage"
    },
    {
      "offset": 3586,
      "version": 0,
      "machine": 332,
      "timeDateStamp": 3741862978,
      "sizeOfData": 39,
      "dllName": "CIMFS.dll",
      "symbolName": "_CimCreateAlternateStream@20",
      "type": "code",
      "nameType": "undecorate",
      "hint": 4,
      "name": "CimCreateAlternateStream"
    },
    {
      "offset": 3706,
      "version": 0,
      "machine": 332,
      "timeDateStamp": 3523641385,
      "sizeOfData": 28,
      "dllName": "CIMFS.dll",
      "symbolName": "_CimCreateFile@16",
      "type": "code",
      "nameType": "undecorate",
      "hint": 5,
      "name": "CimCreateFile"
    },
    {
      "offset": 3814,
      "version": 0,
      "machine": 332,
      "timeDateStamp": 3227522390,
      "sizeOfData": 32,
      "dllName": "CIMFS.dll",
      "symbolName": "_CimCreateHardLink@12",
      "type": "code",
      "nameType": "undecorate",
      "hint": 6,
      "name": "CimCreateHardLink"
    },
    {
      "offset": 3926,
      "version": 0,
      "machine": 332,
      "timeDateStamp": 4012394240,
      "sizeOfData": 29,
      "dllName": "CIMFS.dll",
      "symbolName": "_CimCreateImage@16",
      "type": "code",
      "nameType": "undecorate",
      "hint": 7,
      "name": "CimCreateImage"
    },
    {
      "offset": 4036,
      "version": 0,
      "machine": 332,
      "timeDateStamp": 3821243685,
      "sizeOfData": 34,
      "dllName": "CIMFS.dll",
      "symbolName": "_CimCreateMergedFile@20",
      "type": "code",
      "nameType": "undecorate",
      "hint": 8,
      "name": "CimCreateMergedFile"
    },
    {
      "offset": 4150,
      "version": 0,
      "machine": 332,
      "timeDateStamp": 3767608127,
      "sizeOfData": 27,
      "dllName": "CIMFS.dll",
      "symbolName": "_CimDeletePath@8",
      "type": "code",
      "nameType": "undecorate",
      "hint": 9,
      "name": "CimDeletePath"
    },
    {
      "offset": 4258,
      "version": 0,
      "machine": 332,
      "timeDateStamp": 3993109748,
      "sizeOfData": 30,
      "dllName": "CIMFS.dll",
      "symbolName": "_CimDismountImage@4",
      "type": "code",
      "nameType": "undecorate",
      "hint": 10,
      "name": "CimDismountImage"
    },
    {
      "offset": 4368,
      "version": 0,
      "machine": 332,
      "timeDateStamp": 3287405924,
      "sizeOfData": 28,
      "dllName": "CIMFS.dll",
      "symbolName": "_CimLookupFile@12",
      "type": "code",
      "nameType": "undecorate",
      "hint": 11,
      "name": "CimLookupFile"
    },
    {
      "offset": 4476,
      "version": 0,
      "machine": 332,
      "timeDateStamp": 3471118495,
      "sizeOfData": 33,
      "dllName": "CIMFS.dll",
      "symbolName": "_CimMergeMountImage@16",
      "type": "code",
      "nameType": "undecorate",
      "hint": 12,
      "name": "CimMergeMountImage"
    },
    {
      "offset": 4590,
      "version": 0,
      "machine": 332,
      "timeDateStamp": 3973773481,
      "sizeOfData": 28,
      "dllName": "CIMFS.dll",
      "symbolName": "_CimMountImage@16",
      "type": "code",
      "nameType": "undecorate",
      "hint": 13,
      "name": "CimMountImage"
    },
    {
      "offset": 4698,
      "version": 0,
      "machine": 332,
      "timeDateStamp": 4292122608,
      "sizeOfData": 29,
      "dllName": "CIMFS.dll",
      "symbolName": "_CimWriteStream@12",
      "type": "code",
      "nameType": "undecorate",
      "hint": 14,
      "name": "CimWriteStream"
    }
  ]
}