{
  "dllExports": [],
  "libExports": [
    {
      "name": "_AppendPropVariant@8"
    },
    {
      "name": "_ConvertPropVariant@8"
    },
    {
      "name": "_CopyPropertyStore@12"
    },
    {
      "name": "_CreateNamedPropertyStore@4"
    },
    {
      "name": "_ExtractPropVariant@12"
    },
    {
      "name": "_MFCreateAggregateSource@8"
    },
    {
      "name": "_MFCreateAppSourceProxy@12"
    },
    {
      "name": "_MFCreateAudioRenderer@8"
    },
    {
      "name": "_MFCreateAudioRendererActivate@4"
    },
    {
      "name": "_MFCreateDeviceSource@8"
    },
    {
      "name": "_MFCreateDeviceSourceActivate@8"
    },
    {
      "name": "_MFCreateEncryptedMediaExtensionsStoreActivate@16"
    },
    {
      "name": "_MFCreateExtendedCameraIntrinsicModel@8"
    },
    {
      "name": "_MFCreateExtendedCameraIntrinsics@4"
    },
    {
      "name": "_MFCreateMediaProcessor@4"
    },
    {
      "name": "_MFCreateMediaSession@8"
    },
    {
      "name": "_MFCreatePMPHost@12"
    },
    {
      "name": "_MFCreatePMPMediaSession@16"
    },
    {
      "name": "_MFCreatePMPServer@8"
    },
    {
      "name": "_MFCreatePresentationClock@4"
    },
    {
      "name": "_MFCreateSampleCopierMFT@4"
    },
    {
      "name": "_MFCreateSampleGrabberSinkActivate@12"
    },
    {
      "name": "_MFCreateSequencerSegmentOffset@16"
    },
    {
      "name": "_MFCreateSequencerSource@8"
    },
    {
      "name": "_MFCreateSequencerSourceRemoteStream@12"
    },
    {
      "name": "_MFCreateSimpleTypeHandler@4"
    },
    {
      "name": "_MFCreateStandardQualityManager@4"
    },
    {
      "name": "_MFCreateTopoLoader@4"
    },
    {
      "name": "_MFCreateTopology@4"
    },
    {
      "name": "_MFCreateTopologyNode@8"
    },
    {
      "name": "_MFCreateWMAEncoderActivate@12"
    },
    {
      "name": "_MFCreateWMVEncoderActivate@12"
    },
    {
      "name": "_MFEnumDeviceSources@12"
    },
    {
      "name": "_MFGetMultipleServiceProviders@16"
    },
    {
      "name": "_MFGetService@16"
    },
    {
      "name": "_MFGetTopoNodeCurrentType@16"
    },
    {
      "name": "_MFRequireProtectedEnvironment@4"
    },
    {
      "name": "_MFShutdownObject@4"
    },
    {
      "name": "_MergePropertyStore@12"
    }
  ],
  "libPublicSymbols": [
    {
      "offset": 5798,
      "name": "__IMPORT_DESCRIPTOR_MFCORE"
    },
    {
      "offset": 6348,
      "name": "__NULL_IMPORT_DESCRIPTOR"
    },
    {
      "offset": 6658,
      "name": "MFCORE_NULL_THUNK_DATA"
    },
    {
      "offset": 11434,
      "name": "_MFShutdownObject@4"
    },
    {
      "offset": 11434,
      "name": "__imp__MFShutdownObject@4"
    },
    {
      "offset": 8920,
      "name": "_MFCreatePMPHost@12"
    },
    {
      "offset": 8920,
      "name": "__imp__MFCreatePMPHost@12"
    },
    {
      "offset": 9032,
      "name": "_MFCreatePMPMediaSession@16"
    },
    {
      "offset": 9032,
      "name": "__imp__MFCreatePMPMediaSession@16"
    },
    {
      "offset": 11310,
      "name": "_MFRequireProtectedEnvironment@4"
    },
    {
      "offset": 11310,
      "name": "__imp__MFRequireProtectedEnvironment@4"
    },
    {
      "offset": 7686,
      "name": "_MFCreateAppSourceProxy@12"
    },
    {
      "offset": 7686,
      "name": "__imp__MFCreateAppSourceProxy@12"
    },
    {
      "offset": 9152,
      "name": "_MFCreatePMPServer@8"
    },
    {
      "offset": 9152,
      "name": "__imp__MFCreatePMPServer@8"
    },
    {
      "offset": 9264,
      "name": "_MFCreatePresentationClock@4"
    },
    {
      "offset": 9264,
      "name": "__imp__MFCreatePresentationClock@4"
    },
    {
      "offset": 10008,
      "name": "_MFCreateSimpleTypeHandler@4"
    },
    {
      "offset": 10008,
      "name": "__imp__MFCreateSimpleTypeHandler@4"
    },
    {
      "offset": 7804,
      "name": "_MFCreateAudioRenderer@8"
    },
    {
      "offset": 7804,
      "name": "__imp__MFCreateAudioRenderer@8"
    },
    {
      "offset": 10128,
      "name": "_MFCreateStandardQualityManager@4"
    },
    {
      "offset": 10128,
      "name": "__imp__MFCreateStandardQualityManager@4"
    },
    {
      "offset": 10368,
      "name": "_MFCreateTopology@4"
    },
    {
      "offset": 10368,
      "name": "__imp__MFCreateTopology@4"
    },
    {
      "offset": 10254,
      "name": "_MFCreateTopoLoader@4"
    },
    {
      "offset": 10254,
      "name": "__imp__MFCreateTopoLoader@4"
    },
    {
      "offset": 10480,
      "name": "_MFCreateTopologyNode@8"
    },
    {
      "offset": 10480,
      "name": "__imp__MFCreateTopologyNode@8"
    },
    {
      "offset": 9758,
      "name": "_MFCreateSequencerSource@8"
    },
    {
      "offset": 9758,
      "name": "__imp__MFCreateSequencerSource@8"
    },
    {
      "offset": 9632,
      "name": "_MFCreateSequencerSegmentOffset@16"
    },
    {
      "offset": 9632,
      "name": "__imp__MFCreateSequencerSegmentOffset@16"
    },
    {
      "offset": 9876,
      "name": "_MFCreateSequencerSourceRemoteStream@12"
    },
    {
      "offset": 9876,
      "name": "__imp__MFCreateSequencerSourceRemoteStream@12"
    },
    {
      "offset": 7568,
      "name": "_MFCreateAggregateSource@8"
    },
    {
      "offset": 7568,
      "name": "__imp__MFCreateAggregateSource@8"
    },
    {
      "offset": 8686,
      "name": "_MFCreateMediaProcessor@4"
    },
    {
      "offset": 8686,
      "name": "__imp__MFCreateMediaProcessor@4"
    },
    {
      "offset": 7920,
      "name": "_MFCreateAudioRendererActivate@4"
    },
    {
      "offset": 7920,
      "name": "__imp__MFCreateAudioRendererActivate@4"
    },
    {
      "offset": 10718,
      "name": "_MFCreateWMVEncoderActivate@12"
    },
    {
      "offset": 10718,
      "name": "__imp__MFCreateWMVEncoderActivate@12"
    },
    {
      "offset": 10596,
      "name": "_MFCreateWMAEncoderActivate@12"
    },
    {
      "offset": 10596,
      "name": "__imp__MFCreateWMAEncoderActivate@12"
    },
    {
      "offset": 8804,
      "name": "_MFCreateMediaSession@8"
    },
    {
      "offset": 8804,
      "name": "__imp__MFCreateMediaSession@8"
    },
    {
      "offset": 8284,
      "name": "_MFCreateEncryptedMediaExtensionsStoreActivate@16"
    },
    {
      "offset": 8284,
      "name": "__imp__MFCreateEncryptedMediaExtensionsStoreActivate@16"
    },
    {
      "offset": 11082,
      "name": "_MFGetService@16"
    },
    {
      "offset": 11082,
      "name": "__imp__MFGetService@16"
    },
    {
      "offset": 10956,
      "name": "_MFGetMultipleServiceProviders@16"
    },
    {
      "offset": 10956,
      "name": "__imp__MFGetMultipleServiceProviders@16"
    },
    {
      "offset": 7106,
      "name": "_ConvertPropVariant@8"
    },
    {
      "offset": 7106,
      "name": "__imp__ConvertPropVariant@8"
    },
    {
      "offset": 7454,
      "name": "_ExtractPropVariant@12"
    },
    {
      "offset": 7454,
      "name": "__imp__ExtractPropVariant@12"
    },
    {
      "offset": 6994,
      "name": "_AppendPropVariant@8"
    },
    {
      "offset": 6994,
      "name": "__imp__AppendPropVariant@8"
    },
    {
      "offset": 7334,
      "name": "_CreateNamedPropertyStore@4"
    },
    {
      "offset": 7334,
      "name": "__imp__CreateNamedPropertyStore@4"
    },
    {
      "offset": 7220,
      "name": "_CopyPropertyStore@12"
    },
    {
      "offset": 7220,
      "name": "__imp__CopyPropertyStore@12"
    },
    {
      "offset": 11546,
      "name": "_MergePropertyStore@12"
    },
    {
      "offset": 11546,
      "name": "__imp__MergePropertyStore@12"
    },
    {
      "offset": 9502,
      "name": "_MFCreateSampleGrabberSinkActivate@12"
    },
    {
      "offset": 9502,
      "name": "__imp__MFCreateSampleGrabberSinkActivate@12"
    },
    {
      "offset": 11190,
      "name": "_MFGetTopoNodeCurrentType@16"
    },
    {
      "offset": 11190,
      "name": "__imp__MFGetTopoNodeCurrentType@16"
    },
    {
      "offset": 9384,
      "name": "_MFCreateSampleCopierMFT@4"
    },
    {
      "offset": 9384,
      "name": "__imp__MFCreateSampleCopierMFT@4"
    },
    {
      "offset": 10840,
      "name": "_MFEnumDeviceSources@12"
    },
    {
      "offset": 10840,
      "name": "__imp__MFEnumDeviceSources@12"
    },
    {
      "offset": 8044,
      "name": "_MFCreateDeviceSource@8"
    },
    {
      "offset": 8044,
      "name": "__imp__MFCreateDeviceSource@8"
    },
    {
      "offset": 8160,
      "name": "_MFCreateDeviceSourceActivate@8"
    },
    {
      "offset": 8160,
      "name": "__imp__MFCreateDeviceSourceActivate@8"
    },
    {
      "offset": 8426,
      "name": "_MFCreateExtendedCameraIntrinsicModel@8"
    },
    {
      "offset": 8426,
      "name": "__imp__MFCreateExtendedCameraIntrinsicModel@8"
    },
    {
      "offset": 8558,
      "name": "_MFCreateExtendedCameraIntrinsics@4"
    },
    {
      "offset": 8558,
      "name": "__imp__MFCreateExtendedCameraIntrinsics@4"
    }
  ],
  "libSymbols": [
    {
      "offset": 6994,
      "version": 0,
      "machine": 332,
      "timeDateStamp": 3223526205,
      "sizeOfData": 32,
      "dllName": "MFCORE.dll",
      "symbolName": "_AppendPropVariant@8",
      "type": "code",
      "nameType": "undecorate",
      "hint": 0,
      "name": "AppendPropVariant"
    },
    {
      "offset": 7106,
      "version": 0,
      "machine": 332,
      "timeDateStamp": 3565477431,
      "sizeOfData": 33,
      "dllName": "MFCORE.dll",
      "symbolName": "_ConvertPropVariant@8",
      "type": "code",
      "nameType": "undecorate",
      "hint": 1,
      "name": "ConvertPropVariant"
    },
    {
      "offset": 7220,
      "version": 0,
      "machine": 332,
      "timeDateStamp": 3597222134,
      "sizeOfData": 33,
      "dllName": "MFCORE.dll",
      "symbolName": "_CopyPropertyStore@12",
      "type": "code",
      "nameType": "undecorate",
      "hint": 2,
      "name": "CopyPropertyStore"
    },
    {
      "offset": 7334,
      "version": 0,
      "machine": 332,
      "timeDateStamp": 4098286646,
      "sizeOfData": 39,
      "dllName": "MFCORE.dll",
      "symbolName": "_CreateNamedPropertyStore@4",
      "type": "code",
      "nameType": "undecorate",
      "hint": 3,
      "name": "CreateNamedPropertyStore"
    },
    {
      "offset": 7454,
      "version": 0,
      "machine": 332,
      "timeDateStamp": 3667173024,
      "sizeOfData": 34,
      "dllName": "MFCORE.dll",
      "symbolName": "_ExtractPropVariant@12",
      "type": "code",
      "nameType": "undecorate",
      "hint": 9,
      "name": "ExtractPropVariant"
    },
    {
      "offset": 7568,
      "version": 0,
      "machine": 332,
      "timeDateStamp": 3425195456,
      "sizeOfData": 38,
      "dllName": "MFCORE.dll",
      "symbolName": "_MFCreateAggregateSource@8",
      "type": "code",
      "nameType": "undecorate",
      "hint": 13,
      "name": "MFCreateAggregateSource"
    },
    {
      "offset": 7686,
      "version": 0,
      "machine": 332,
      "timeDateStamp": 4091758136,
      "sizeOfData": 38,
      "dllName": "MFCORE.dll",
      "symbolName": "_MFCreateAppSourceProxy@12",
      "type": "code",
      "nameType": "undecorate",
      "hint": 14,
      "name": "MFCreateAppSourceProxy"
    },
    {
      "offset": 7804,
      "version": 0,
      "machine": 332,
      "timeDateStamp": 3914344151,
      "sizeOfData": 36,
      "dllName": "MFCORE.dll",
      "symbolName": "_MFCreateAudioRenderer@8",
      "type": "code",
      "nameType": "undecorate",
      "hint": 15,
      "name": "MFCreateAudioRenderer"
    },
    {
      "offset": 7920,
      "version": 0,
      "machine": 332,
      "timeDateStamp": 3964643971,
      "sizeOfData": 44,
      "dllName": "MFCORE.dll",
      "symbolName": "_MFCreateAudioRendererActivate@4",
      "type": "code",
      "nameType": "undecorate",
      "hint": 16,
      "name": "MFCreateAudioRendererActivate"
    },
    {
      "offset": 8044,
      "version": 0,
      "machine": 332,
      "timeDateStamp": 4206837108,
      "sizeOfData": 35,
      "dllName": "MFCORE.dll",
      "symbolName": "_MFCreateDeviceSource@8",
      "type": "code",
      "nameType": "undecorate",
      "hint": 17,
      "name": "MFCreateDeviceSource"
    },
    {
      "offset": 8160,
      "version": 0,
      "machine": 332,
      "timeDateStamp": 4124328454,
      "sizeOfData": 43,
      "dllName": "MFCORE.dll",
      "symbolName": "_MFCreateDeviceSourceActivate@8",
      "type": "code",
      "nameType": "undecorate",
      "hint": 18,
      "name": "MFCreateDeviceSourceActivate"
    },
    {
      "offset": 8284,
      "version": 0,
      "machine": 332,
      "timeDateStamp": 3446689290,
      "sizeOfData": 61,
      "dllName": "MFCORE.dll",
      "symbolName": "_MFCreateEncryptedMediaExtensionsStoreActivate@16",
      "type": "code",
      "nameType": "undecorate",
      "hint": 19,
      "name": "MFCreateEncryptedMediaExtensionsStoreActivate"
    },
    {
      "offset": 8426,
      "version": 0,
      "machine": 332,
      "timeDateStamp": 4143879784,
      "sizeOfData": 51,
      "dllName": "MFCORE.dll",
      "symbolName": "_MFCreateExtendedCameraIntrinsicModel@8",
      "type": "code",
      "nameType": "undecorate",
      "hint": 20,
      "name": "MFCreateExtendedCameraIntrinsicModel"
    },
    {
      "offset": 8558,
      "version": 0,
      "machine": 332,
      "timeDateStamp": 3597402069,
      "sizeOfData": 47,
      "dllName": "MFCORE.dll",
      "symbolName": "_MFCreateExtendedCameraIntrinsics@4",
      "type": "code",
      "nameType": "undecorate",
      "hint": 21,
      "name": "MFCreateExtendedCameraIntrinsics"
    },
    {
      "offset": 8686,
      "version": 0,
      "machine": 332,
      "timeDateStamp": 3871839744,
      "sizeOfData": 37,
      "dllName": "MFCORE.dll",
      "symbolName": "_MFCreateMediaProcessor@4",
      "type": "code",
      "nameType": "undecorate",
      "hint": 24,
      "name": "MFCreateMediaProcessor"
    },
    {
      "offset": 8804,
      "version": 0,
      "machine": 332,
      "timeDateStamp": 3699414305,
      "sizeOfData": 35,
      "dllName": "MFCORE.dll",
      "symbolName": "_MFCreateMediaSession@8",
      "type": "code",
      "nameType": "undecorate",
      "hint": 25,
      "name": "MFCreateMediaSession"
    },
    {
      "offset": 8920,
      "version": 0,
      "machine": 332,
      "timeDateStamp": 3886099933,
      "sizeOfData": 31,
      "dllName": "MFCORE.dll",
      "symbolName": "_MFCreatePMPHost@12",
      "type": "code",
      "nameType": "undecorate",
      "hint": 26,
      "name": "MFCreatePMPHost"
    },
    {
      "offset": 9032,
      "version": 0,
      "machine": 332,
      "timeDateStamp": 3234066390,
      "sizeOfData": 39,
      "dllName": "MFCORE.dll",
      "symbolName": "_MFCreatePMPMediaSession@16",
      "type": "code",
      "nameType": "undecorate",
      "hint": 27,
      "name": "MFCreatePMPMediaSession"
    },
    {
      "offset": 9152,
      "version": 0,
      "machine": 332,
      "timeDateStamp": 4235294762,
      "sizeOfData": 32,
      "dllName": "MFCORE.dll",
      "symbolName": "_MFCreatePMPServer@8",
      "type": "code",
      "nameType": "undecorate",
      "hint": 28,
      "name": "MFCreatePMPServer"
    },
    {
      "offset": 9264,
      "version": 0,
      "machine": 332,
      "timeDateStamp": 3659154296,
      "sizeOfData": 40,
      "dllName": "MFCORE.dll",
      "symbolName": "_MFCreatePresentationClock@4",
      "type": "code",
      "nameType": "undecorate",
      "hint": 29,
      "name": "MFCreatePresentationClock"
    },
    {
      "offset": 9384,
      "version": 0,
      "machine": 332,
      "timeDateStamp": 3705980391,
      "sizeOfData": 38,
      "dllName": "MFCORE.dll",
      "symbolName": "_MFCreateSampleCopierMFT@4",
      "type": "code",
      "nameType": "undecorate",
      "hint": 31,
      "name": "MFCreateSampleCopierMFT"
    },
    {
      "offset": 9502,
      "version": 0,
      "machine": 332,
      "timeDateStamp": 3310858707,
      "sizeOfData": 49,
      "dllName": "MFCORE.dll",
      "symbolName": "_MFCreateSampleGrabberSinkActivate@12",
      "type": "code",
      "nameType": "undecorate",
      "hint": 32,
      "name": "MFCreateSampleGrabberSinkActivate"
    },
    {
      "offset": 9632,
      "version": 0,
      "machine": 332,
      "timeDateStamp": 3906554300,
      "sizeOfData": 46,
      "dllName": "MFCORE.dll",
      "symbolName": "_MFCreateSequencerSegmentOffset@16",
      "type": "code",
      "nameType": "undecorate",
      "hint": 33,
      "name": "MFCreateSequencerSegmentOffset"
    },
    {
      "offset": 9758,
      "version": 0,
      "machine": 332,
      "timeDateStamp": 3612349077,
      "sizeOfData": 38,
      "dllName": "MFCORE.dll",
      "symbolName": "_MFCreateSequencerSource@8",
      "type": "code",
      "nameType": "undecorate",
      "hint": 34,
      "name": "MFCreateSequencerSource"
    },
    {
      "offset": 9876,
      "version": 0,
      "machine": 332,
      "timeDateStamp": 4035469755,
      "sizeOfData": 51,
      "dllName": "MFCORE.dll",
      "symbolName": "_MFCreateSequencerSourceRemoteStream@12",
      "type": "code",
      "nameType": "undecorate",
      "hint": 35,
      "name": "MFCreateSequencerSourceRemoteStream"
    },
    {
      "offset": 10008,
      "version": 0,
      "machine": 332,
      "timeDateStamp": 3992820457,
      "sizeOfData": 40,
      "dllName": "MFCORE.dll",
      "symbolName": "_MFCreateSimpleTypeHandler@4",
      "type": "code",
      "nameType": "undecorate",
      "hint": 36,
      "name": "MFCreateSimpleTypeHandler"
    },
    {
      "offset": 10128,
      "version": 0,
      "machine": 332,
      "timeDateStamp": 4057623082,
      "sizeOfData": 45,
      "dllName": "MFCORE.dll",
      "symbolName": "_MFCreateStandardQualityManager@4",
      "type": "code",
      "nameType": "undecorate",
      "hint": 38,
      "name": "MFCreateStandardQualityManager"
    },
    {
      "offset": 10254,
      "version": 0,
      "machine": 332,
      "timeDateStamp": 3234156631,
      "sizeOfData": 33,
      "dllName": "MFCORE.dll",
      "symbolName": "_MFCreateTopoLoader@4",
      "type": "code",
      "nameType": "undecorate",
      "hint": 39,
      "name": "MFCreateTopoLoader"
    },
    {
      "offset": 10368,
      "version": 0,
      "machine": 332,
      "timeDateStamp": 3872630500,
      "sizeOfData": 31,
      "dllName": "MFCORE.dll",
      "symbolName": "_MFCreateTopology@4",
      "type": "code",
      "nameType": "undecorate",
      "hint": 40,
      "name": "MFCreateTopology"
    },
    {
      "offset": 10480,
      "version": 0,
      "machine": 332,
      "timeDateStamp": 3435122869,
      "sizeOfData": 35,
      "dllName": "MFCORE.dll",
      "symbolName": "_MFCreateTopologyNode@8",
      "type": "code",
      "nameType": "undecorate",
      "hint": 41,
      "name": "MFCreateTopologyNode"
    },
    {
      "offset": 10596,
      "version": 0,
      "machine": 332,
      "timeDateStamp": 3305561152,
      "sizeOfData": 42,
      "dllName": "MFCORE.dll",
      "symbolName": "_MFCreateWMAEncoderActivate@12",
      "type": "code",
      "nameType": "undecorate",
      "hint": 43,
      "name": "MFCreateWMAEncoderActivate"
    },
    {
      "offset": 10718,
      "version": 0,
      "machine": 332,
      "timeDateStamp": 4058432015,
      "sizeOfData": 42,
      "dllName": "MFCORE.dll",
      "symbolName": "_MFCreateWMVEncoderActivate@12",
      "type": "code",
      "nameType": "undecorate",
      "hint": 44,
      "name": "MFCreateWMVEncoderActivate"
    },
    {
      "offset": 10840,
      "version": 0,
      "machine": 332,
      "timeDateStamp": 3789928907,
      "sizeOfData": 35,
      "dllName": "MFCORE.dll",
      "symbolName": "_MFEnumDeviceSources@12",
      "type": "code",
      "nameType": "undecorate",
      "hint": 45,
      "name": "MFEnumDeviceSources"
    },
    {
      "offset": 10956,
      "version": 0,
      "machine": 332,
      "timeDateStamp": 3812041343,
      "sizeOfData": 45,
      "dllName": "MFCORE.dll",
      "symbolName": "_MFGetMultipleServiceProviders@16",
      "type": "code",
      "nameType": "undecorate",
      "hint": 46,
      "name": "MFGetMultipleServiceProviders"
    },
    {
      "offset": 11082,
      "version": 0,
      "machine": 332,
      "timeDateStamp": 3449499162,
      "sizeOfData": 28,
      "dllName": "MFCORE.dll",
      "symbolName": "_MFGetService@16",
      "type": "code",
      "nameType": "undecorate",
      "hint": 47,
      "name": "MFGetService"
    },
    {
      "offset": 11190,
      "version": 0,
      "machine": 332,
      "timeDateStamp": 3329783133,
      "sizeOfData": 40,
      "dllName": "MFCORE.dll",
      "symbolName": "_MFGetTopoNodeCurrentType@16",
      "type": "code",
      "nameType": "undecorate",
      "hint": 48,
      "name": "MFGetTopoNodeCurrentType"
    },
    {
      "offset": 11310,
      "version": 0,
      "machine": 332,
      "timeDateStamp": 3743641883,
      "sizeOfData": 44,
      "dllName": "MFCORE.dll",
      "symbolName": "_MFRequireProtectedEnvironment@4",
      "type": "code",
      "nameType": "undecorate",
      "hint": 50,
      "name": "MFRequireProtectedEnvironment"
    },
    {
      "offset": 11434,
      "version": 0,
      "machine": 332,
      "timeDateStamp": 3335760388,
      "sizeOfData": 31,
      "dllName": "MFCORE.dll",
      "symbolName": "_MFShutdownObject@4",
      "type": "code",
      "nameType": "undecorate",
      "hint": 51,
      "name": "MFShutdownObject"
    },
    {
      "offset": 11546,
      "version": 0,
      "machine": 332,
      "timeDateStamp": 4019818988,
      "sizeOfData": 34,
      "dllName": "MFCORE.dll",
      "symbolName": "_MergePropertyStore@12",
      "type": "code",
      "nameType": "undecorate",
      "hint": 52,
      "name": "MergePropertyStore"
    }
  ]
}