{
  "dllExports": [],
  "libExports": [
    {
      "name": "_EmptyWorkingSet@4"
    },
    {
      "name": "_EnumDeviceDrivers@12"
    },
    {
      "name": "_EnumPageFilesA@8"
    },
    {
      "name": "_EnumPageFilesW@8"
    },
    {
      "name": "_EnumProcessModules@16"
    },
    {
      "name": "_EnumProcessModulesEx@20"
    },
    {
      "name": "_EnumProcesses@12"
    },
    {
      "name": "_GetDeviceDriverBaseNameA@12"
    },
    {
      "name": "_GetDeviceDriverBaseNameW@12"
    },
    {
      "name": "_GetDeviceDriverFileNameA@12"
    },
    {
      "name": "_GetDeviceDriverFileNameW@12"
    },
    {
      "name": "_GetMappedFileNameA@16"
    },
    {
      "name": "_GetMappedFileNameW@16"
    },
    {
      "name": "_GetModuleBaseNameA@16"
    },
    {
      "name": "_GetModuleBaseNameW@16"
    },
    {
      "name": "_GetModuleFileNameExA@16"
    },
    {
      "name": "_GetModuleFileNameExW@16"
    },
    {
      "name": "_GetModuleInformation@16"
    },
    {
      "name": "_GetPerformanceInfo@8"
    },
    {
      "name": "_GetProcessImageFileNameA@12"
    },
    {
      "name": "_GetProcessImageFileNameW@12"
    },
    {
      "name": "_GetProcessMemoryInfo@12"
    },
    {
      "name": "_GetWsChanges@12"
    },
    {
      "name": "_GetWsChangesEx@12"
    },
    {
      "name": "_InitializeProcessForWsWatch@4"
    },
    {
      "name": "_QueryWorkingSet@12"
    },
    {
      "name": "_QueryWorkingSetEx@12"
    }
  ],
  "libPublicSymbols": [
    {
      "offset": 3634,
      "name": "__IMPORT_DESCRIPTOR_PSAPI"
    },
    {
      "offset": 4180,
      "name": "__NULL_IMPORT_DESCRIPTOR"
    },
    {
      "offset": 4488,
      "name": "PSAPI_NULL_THUNK_DATA"
    },
    {
      "offset": 5260,
      "name": "_EnumProcessModules@16"
    },
    {
      "offset": 5260,
      "name": "__imp__EnumProcessModules@16"
    },
    {
      "offset": 5374,
      "name": "_EnumProcessModulesEx@20"
    },
    {
      "offset": 5374,
      "name": "__imp__EnumProcessModulesEx@20"
    },
    {
      "offset": 5490,
      "name": "_EnumProcesses@12"
    },
    {
      "offset": 5490,
      "name": "__imp__EnumProcesses@12"
    },
    {
      "offset": 6306,
      "name": "_GetModuleBaseNameA@16"
    },
    {
      "offset": 6306,
      "name": "__imp__GetModuleBaseNameA@16"
    },
    {
      "offset": 6420,
      "name": "_GetModuleBaseNameW@16"
    },
    {
      "offset": 6420,
      "name": "__imp__GetModuleBaseNameW@16"
    },
    {
      "offset": 6534,
      "name": "_GetModuleFileNameExA@16"
    },
    {
      "offset": 6534,
      "name": "__imp__GetModuleFileNameExA@16"
    },
    {
      "offset": 6650,
      "name": "_GetModuleFileNameExW@16"
    },
    {
      "offset": 6650,
      "name": "__imp__GetModuleFileNameExW@16"
    },
    {
      "offset": 6766,
      "name": "_GetModuleInformation@16"
    },
    {
      "offset": 6766,
      "name": "__imp__GetModuleInformation@16"
    },
    {
      "offset": 7234,
      "name": "_GetProcessMemoryInfo@12"
    },
    {
      "offset": 7234,
      "name": "__imp__GetProcessMemoryInfo@12"
    },
    {
      "offset": 4822,
      "name": "_EmptyWorkingSet@4"
    },
    {
      "offset": 4822,
      "name": "__imp__EmptyWorkingSet@4"
    },
    {
      "offset": 7690,
      "name": "_QueryWorkingSet@12"
    },
    {
      "offset": 7690,
      "name": "__imp__QueryWorkingSet@12"
    },
    {
      "offset": 7800,
      "name": "_QueryWorkingSetEx@12"
    },
    {
      "offset": 7800,
      "name": "__imp__QueryWorkingSetEx@12"
    },
    {
      "offset": 6078,
      "name": "_GetMappedFileNameA@16"
    },
    {
      "offset": 6078,
      "name": "__imp__GetMappedFileNameA@16"
    },
    {
      "offset": 6192,
      "name": "_GetMappedFileNameW@16"
    },
    {
      "offset": 6192,
      "name": "__imp__GetMappedFileNameW@16"
    },
    {
      "offset": 4932,
      "name": "_EnumDeviceDrivers@12"
    },
    {
      "offset": 4932,
      "name": "__imp__EnumDeviceDrivers@12"
    },
    {
      "offset": 5598,
      "name": "_GetDeviceDriverBaseNameA@12"
    },
    {
      "offset": 5598,
      "name": "__imp__GetDeviceDriverBaseNameA@12"
    },
    {
      "offset": 5718,
      "name": "_GetDeviceDriverBaseNameW@12"
    },
    {
      "offset": 5718,
      "name": "__imp__GetDeviceDriverBaseNameW@12"
    },
    {
      "offset": 5838,
      "name": "_GetDeviceDriverFileNameA@12"
    },
    {
      "offset": 5838,
      "name": "__imp__GetDeviceDriverFileNameA@12"
    },
    {
      "offset": 5958,
      "name": "_GetDeviceDriverFileNameW@12"
    },
    {
      "offset": 5958,
      "name": "__imp__GetDeviceDriverFileNameW@12"
    },
    {
      "offset": 7568,
      "name": "_InitializeProcessForWsWatch@4"
    },
    {
      "offset": 7568,
      "name": "__imp__InitializeProcessForWsWatch@4"
    },
    {
      "offset": 7350,
      "name": "_GetWsChanges@12"
    },
    {
      "offset": 7350,
      "name": "__imp__GetWsChanges@12"
    },
    {
      "offset": 7458,
      "name": "_GetWsChangesEx@12"
    },
    {
      "offset": 7458,
      "name": "__imp__GetWsChangesEx@12"
    },
    {
      "offset": 6882,
      "name": "_GetPerformanceInfo@8"
    },
    {
      "offset": 6882,
      "name": "__imp__GetPerformanceInfo@8"
    },
    {
      "offset": 5152,
      "name": "_EnumPageFilesW@8"
    },
    {
      "offset": 5152,
      "name": "__imp__EnumPageFilesW@8"
    },
    {
      "offset": 5044,
      "name": "_EnumPageFilesA@8"
    },
    {
      "offset": 5044,
      "name": "__imp__EnumPageFilesA@8"
    },
    {
      "offset": 6994,
      "name": "_GetProcessImageFileNameA@12"
    },
    {
      "offset": 6994,
      "name": "__imp__GetProcessImageFileNameA@12"
    },
    {
      "offset": 7114,
      "name": "_GetProcessImageFileNameW@12"
    },
    {
      "offset": 7114,
      "name": "__imp__GetProcessImageFileNameW@12"
    }
  ],
  "libSymbols": [
    {
      "offset": 4822,
      "version": 0,
      "machine": 332,
      "timeDateStamp": 3466317703,
      "sizeOfData": 29,
      "dllName": "PSAPI.DLL",
      "symbolName": "_EmptyWorkingSet@4",
      "type": "code",
      "nameType": "undecorate",
      "hint": 0,
      "name": "EmptyWorkingSet"
    },
    {
      "offset": 4932,
      "version": 0,
      "machine": 332,
      "timeDateStamp": 4069629829,
      "sizeOfData": 32,
      "dllName": "PSAPI.DLL",
      "symbolName": "_EnumDeviceDrivers@12",
      "type": "code",
      "nameType": "undecorate",
      "hint": 1,
      "name": "EnumDeviceDrivers"
    },
    {
      "offset": 5044,
      "version": 0,
      "machine": 332,
      "timeDateStamp": 3644242074,
      "sizeOfData": 28,
      "dllName": "PSAPI.DLL",
      "symbolName": "_EnumPageFilesA@8",
      "type": "code",
      "nameType": "undecorate",
      "hint": 2,
      "name": "EnumPageFilesA"
    },
    {
      "offset": 5152,
      "version": 0,
      "machine": 332,
      "timeDateStamp": 4181178041,
      "sizeOfData": 28,
      "dllName": "PSAPI.DLL",
      "symbolName": "_EnumPageFilesW@8",
      "type": "code",
      "nameType": "undecorate",
      "hint": 3,
      "name": "EnumPageFilesW"
    },
    {
      "offset": 5260,
      "version": 0,
      "machine": 332,
      "timeDateStamp": 3329118124,
      "sizeOfData": 33,
      "dllName": "PSAPI.DLL",
      "symbolName": "_EnumProcessModules@16",
      "type": "code",
      "nameType": "undecorate",
      "hint": 4,
      "name": "EnumProcessModules"
    },
    {
      "offset": 5374,
      "version": 0,
      "machine": 332,
      "timeDateStamp": 3592950111,
      "sizeOfData": 35,
      "dllName": "PSAPI.DLL",
      "symbolName": "_EnumProcessModulesEx@20",
      "type": "code",
      "nameType": "undecorate",
      "hint": 5,
      "name": "EnumProcessModulesEx"
    },
    {
      "offset": 5490,
      "version": 0,
      "machine": 332,
      "timeDateStamp": 4194044251,
      "sizeOfData": 28,
      "dllName": "PSAPI.DLL",
      "symbolName": "_EnumProcesses@12",
      "type": "code",
      "nameType": "undecorate",
      "hint": 6,
      "name": "EnumProcesses"
    },
    {
      "offset": 5598,
      "version": 0,
      "machine": 332,
      "timeDateStamp": 3542696923,
      "sizeOfData": 39,
      "dllName": "PSAPI.DLL",
      "symbolName": "_GetDeviceDriverBaseNameA@12",
      "type": "code",
      "nameType": "undecorate",
      "hint": 7,
      "name": "GetDeviceDriverBaseNameA"
    },
    {
      "offset": 5718,
      "version": 0,
      "machine": 332,
      "timeDateStamp": 4212096695,
      "sizeOfData": 39,
      "dllName": "PSAPI.DLL",
      "symbolName": "_GetDeviceDriverBaseNameW@12",
      "type": "code",
      "nameType": "undecorate",
      "hint": 8,
      "name": "GetDeviceDriverBaseNameW"
    },
    {
      "offset": 5838,
      "version": 0,
      "machine": 332,
      "timeDateStamp": 3598037842,
      "sizeOfData": 39,
      "dllName": "PSAPI.DLL",
      "symbolName": "_GetDeviceDriverFileNameA@12",
      "type": "code",
      "nameType": "undecorate",
      "hint": 9,
      "name": "GetDeviceDriverFileNameA"
    },
    {
      "offset": 5958,
      "version": 0,
      "machine": 332,
      "timeDateStamp": 3279009801,
      "sizeOfData": 39,
      "dllName": "PSAPI.DLL",
      "symbolName": "_GetDeviceDriverFileNameW@12",
      "type": "code",
      "nameType": "undecorate",
      "hint": 10,
      "name": "GetDeviceDriverFileNameW"
    },
    {
      "offset": 6078,
      "version": 0,
      "machine": 332,
      "timeDateStamp": 3387019741,
      "sizeOfData": 33,
      "dllName": "PSAPI.DLL",
      "symbolName": "_GetMappedFileNameA@16",
      "type": "code",
      "nameType": "undecorate",
      "hint": 11,
      "name": "GetMappedFileNameA"
    },
    {
      "offset": 6192,
      "version": 0,
      "machine": 332,
      "timeDateStamp": 4018469550,
      "sizeOfData": 33,
      "dllName": "PSAPI.DLL",
      "symbolName": "_GetMappedFileNameW@16",
      "type": "code",
      "nameType": "undecorate",
      "hint": 12,
      "name": "GetMappedFileNameW"
    },
    {
      "offset": 6306,
      "version": 0,
      "machine": 332,
      "timeDateStamp": 3372455770,
      "sizeOfData": 33,
      "dllName": "PSAPI.DLL",
      "symbolName": "_GetModuleBaseNameA@16",
      "type": "code",
      "nameType": "undecorate",
      "hint": 13,
      "name": "GetModuleBaseNameA"
    },
    {
      "offset": 6420,
      "version": 0,
      "machine": 332,
      "timeDateStamp": 3773340185,
      "sizeOfData": 33,
      "dllName": "PSAPI.DLL",
      "symbolName": "_GetModuleBaseNameW@16",
      "type": "code",
      "nameType": "undecorate",
      "hint": 14,
      "name": "GetModuleBaseNameW"
    },
    {
      "offset": 6534,
      "version": 0,
      "machine": 332,
      "timeDateStamp": 4281612897,
      "sizeOfData": 35,
      "dllName": "PSAPI.DLL",
      "symbolName": "_GetModuleFileNameExA@16",
      "type": "code",
      "nameType": "undecorate",
      "hint": 15,
      "name": "GetModuleFileNameExA"
    },
    {
      "offset": 6650,
      "version": 0,
      "machine": 332,
      "timeDateStamp": 3537635289,
      "sizeOfData": 35,
      "dllName": "PSAPI.DLL",
      "symbolName": "_GetModuleFileNameExW@16",
      "type": "code",
      "nameType": "undecorate",
      "hint": 16,
      "name": "GetModuleFileNameExW"
    },
    {
      "offset": 6766,
      "version": 0,
      "machine": 332,
      "timeDateStamp": 3393430658,
      "sizeOfData": 35,
      "dllName": "PSAPI.DLL",
      "symbolName": "_GetModuleInformation@16",
      "type": "code",
      "nameType": "undecorate",
      "hint": 17,
      "name": "GetModuleInformation"
    },
    {
      "offset": 6882,
      "version": 0,
      "machine": 332,
      "timeDateStamp": 4095468117,
      "sizeOfData": 32,
      "dllName": "PSAPI.DLL",
      "symbolName": "_GetPerformanceInfo@8",
      "type": "code",
      "nameType": "undecorate",
      "hint": 18,
      "name": "GetPerformanceInfo"
    },
    {
      "offset": 6994,
      "version": 0,
      "machine": 332,
      "timeDateStamp": 4104255947,
      "sizeOfData": 39,
      "dllName": "PSAPI.DLL",
      "symbolName": "_GetProcessImageFileNameA@12",
      "type": "code",
      "nameType": "undecorate",
      "hint": 19,
      "name": "GetProcessImageFileNameA"
    },
    {
      "offset": 7114,
      "version": 0,
      "machine": 332,
      "timeDateStamp": 3797356695,
      "sizeOfData": 39,
      "dllName": "PSAPI.DLL",
      "symbolName": "_GetProcessImageFileNameW@12",
      "type": "code",
      "nameType": "undecorate",
      "hint": 20,
      "name": "GetProcessImageFileNameW"
    },
    {
      "offset": 7234,
      "version": 0,
      "machine": 332,
      "timeDateStamp": 3914143710,
      "sizeOfData": 35,
      "dllName": "PSAPI.DLL",
      "symbolName": "_GetProcessMemoryInfo@12",
      "type": "code",
      "nameType": "undecorate",
      "hint": 21,
      "name": "GetProcessMemoryInfo"
    },
    {
      "offset": 7350,
      "version": 0,
      "machine": 332,
      "timeDateStamp": 3317294288,
      "sizeOfData": 27,
      "dllName": "PSAPI.DLL",
      "symbolName": "_GetWsChanges@12",
      "type": "code",
      "nameType": "undecorate",
      "hint": 22,
      "name": "GetWsChanges"
    },
    {
      "offset": 7458,
      "version": 0,
      "machine": 332,
      "timeDateStamp": 3959618484,
      "sizeOfData": 29,
      "dllName": "PSAPI.DLL",
      "symbolName": "_GetWsChangesEx@12",
      "type": "code",
      "nameType": "undecorate",
      "hint": 23,
      "name": "GetWsChangesEx"
    },
    {
      "offset": 7568,
      "version": 0,
      "machine": 332,
      "timeDateStamp": 3746482065,
      "sizeOfData": 41,
      "dllName": "PSAPI.DLL",
      "symbolName": "_InitializeProcessForWsWatch@4",
      "type": "code",
      "nameType": "undecorate",
      "hint": 24,
      "name": "InitializeProcessForWsWatch"
    },
    {
      "offset": 7690,
      "version": 0,
      "machine": 332,
      "timeDateStamp": 3566583032,
      "sizeOfData": 30,
      "dllName": "PSAPI.DLL",
      "symbolName": "_QueryWorkingSet@12",
      "type": "code",
      "nameType": "undecorate",
      "hint": 25,
      "name": "QueryWorkingSet"
    },
    {
      "offset": 7800,
      "version": 0,
      "machine": 332,
      "timeDateStamp": 4079197875,
      "sizeOfData": 32,
      "dllName": "PSAPI.DLL",
      "symbolName": "_QueryWorkingSetEx@12",
      "type": "code",
      "nameType": "undecorate",
      "hint": 26,
      "name": "QueryWorkingSetEx"
    }
  ]
}