{
  "dllExports": [],
  "libExports": [],
  "libPublicSymbols": [
    {
      "offset": 11478,
      "name": "_CLSID_SpAudioFormat"
    },
    {
      "offset": 11478,
      "name": "_CLSID_SpCFGEngine"
    },
    {
      "offset": 11478,
      "name": "_CLSID_SpCommunicator"
    },
    {
      "offset": 11478,
      "name": "_CLSID_SpCompressedLexicon"
    },
    {
      "offset": 11478,
      "name": "_CLSID_SpCustomStream"
    },
    {
      "offset": 11478,
      "name": "_CLSID_SpDMOAudioIn"
    },
    {
      "offset": 11478,
      "name": "_CLSID_SpDSoundAudioEnum"
    },
    {
      "offset": 11478,
      "name": "_CLSID_SpDSoundAudioIn"
    },
    {
      "offset": 11478,
      "name": "_CLSID_SpDSoundAudioOut"
    },
    {
      "offset": 11478,
      "name": "_CLSID_SpDataKey"
    },
    {
      "offset": 11478,
      "name": "_CLSID_SpFDProvider"
    },
    {
      "offset": 11478,
      "name": "_CLSID_SpFileStream"
    },
    {
      "offset": 11478,
      "name": "_CLSID_SpGramCompBackend"
    },
    {
      "offset": 11478,
      "name": "_CLSID_SpGrammarCompiler"
    },
    {
      "offset": 11478,
      "name": "_CLSID_SpGrammarReferences"
    },
    {
      "offset": 11478,
      "name": "_CLSID_SpITNProcessor"
    },
    {
      "offset": 11478,
      "name": "_CLSID_SpInProcRecoContext"
    },
    {
      "offset": 11478,
      "name": "_CLSID_SpInprocRecognizer"
    },
    {
      "offset": 11478,
      "name": "_CLSID_SpLexicon"
    },
    {
      "offset": 11478,
      "name": "_CLSID_SpMMAudioEnum"
    },
    {
      "offset": 11478,
      "name": "_CLSID_SpMMAudioIn"
    },
    {
      "offset": 11478,
      "name": "_CLSID_SpMMAudioInLegacy"
    },
    {
      "offset": 11478,
      "name": "_CLSID_SpMMAudioOut"
    },
    {
      "offset": 11478,
      "name": "_CLSID_SpMSSemanticInterpretation"
    },
    {
      "offset": 11478,
      "name": "_CLSID_SpMemoryStream"
    },
    {
      "offset": 11478,
      "name": "_CLSID_SpNotifyTranslator"
    },
    {
      "offset": 11478,
      "name": "_CLSID_SpNullPhoneConverter"
    },
    {
      "offset": 11478,
      "name": "_CLSID_SpObjectToken"
    },
    {
      "offset": 11478,
      "name": "_CLSID_SpObjectTokenCategory"
    },
    {
      "offset": 11478,
      "name": "_CLSID_SpObjectTokenEnum"
    },
    {
      "offset": 11478,
      "name": "_CLSID_SpPhoneConverter"
    },
    {
      "offset": 11478,
      "name": "_CLSID_SpPhoneticAlphabetConverter"
    },
    {
      "offset": 11478,
      "name": "_CLSID_SpPhraseBuilder"
    },
    {
      "offset": 11478,
      "name": "_CLSID_SpPhraseInfoBuilder"
    },
    {
      "offset": 11478,
      "name": "_CLSID_SpResourceManager"
    },
    {
      "offset": 11478,
      "name": "_CLSID_SpSapiServer"
    },
    {
      "offset": 11478,
      "name": "_CLSID_SpSharedRecoContext"
    },
    {
      "offset": 11478,
      "name": "_CLSID_SpSharedRecognizer"
    },
    {
      "offset": 11478,
      "name": "_CLSID_SpShortcut"
    },
    {
      "offset": 11478,
      "name": "_CLSID_SpStream"
    },
    {
      "offset": 11478,
      "name": "_CLSID_SpStreamFormatConverter"
    },
    {
      "offset": 11478,
      "name": "_CLSID_SpTaskManager"
    },
    {
      "offset": 11478,
      "name": "_CLSID_SpTextSelectionInformation"
    },
    {
      "offset": 11478,
      "name": "_CLSID_SpUnCompressedLexicon"
    },
    {
      "offset": 11478,
      "name": "_CLSID_SpVoice"
    },
    {
      "offset": 11478,
      "name": "_CLSID_SpW3CGrammarCompiler"
    },
    {
      "offset": 11478,
      "name": "_CLSID_SpW3CSemanticInterpretation"
    },
    {
      "offset": 11478,
      "name": "_CLSID_SpWaveFormatEx"
    },
    {
      "offset": 11478,
      "name": "_CLSID__SpRecoMaster"
    },
    {
      "offset": 11478,
      "name": "_CLSID__SpSharedRecoInst"
    },
    {
      "offset": 11478,
      "name": "_DIID__ISpeechRecoContextEvents"
    },
    {
      "offset": 11478,
      "name": "_DIID__ISpeechVoiceEvents"
    },
    {
      "offset": 11478,
      "name": "_IID_IEnumSpObjectTokens"
    },
    {
      "offset": 11478,
      "name": "_IID_ISpAudio"
    },
    {
      "offset": 11478,
      "name": "_IID_ISpCFGEngine"
    },
    {
      "offset": 11478,
      "name": "_IID_ISpCFGInterpreter"
    },
    {
      "offset": 11478,
      "name": "_IID_ISpCFGInterpreterSite"
    },
    {
      "offset": 11478,
      "name": "_IID_ISpCallReceiver"
    },
    {
      "offset": 11478,
      "name": "_IID_ISpCallSender"
    },
    {
      "offset": 11478,
      "name": "_IID_ISpCategory"
    },
    {
      "offset": 11478,
      "name": "_IID_ISpCommunicator"
    },
    {
      "offset": 11478,
      "name": "_IID_ISpCommunicatorInit"
    },
    {
      "offset": 11478,
      "name": "_IID_ISpContainerLexicon"
    },
    {
      "offset": 11478,
      "name": "_IID_ISpDMOAudioConfig"
    },
    {
      "offset": 11478,
      "name": "_IID_ISpDSoundAudio"
    },
    {
      "offset": 11478,
      "name": "_IID_ISpDataCollector"
    },
    {
      "offset": 11478,
      "name": "_IID_ISpDataKey"
    },
    {
      "offset": 11478,
      "name": "_IID_ISpDisplayAlternates"
    },
    {
      "offset": 11478,
      "name": "_IID_ISpEnginePronunciation"
    },
    {
      "offset": 11478,
      "name": "_IID_ISpErrorLog"
    },
    {
      "offset": 11478,
      "name": "_IID_ISpEventSink"
    },
    {
      "offset": 11478,
      "name": "_IID_ISpEventSource"
    },
    {
      "offset": 11478,
      "name": "_IID_ISpEventSource2"
    },
    {
      "offset": 11478,
      "name": "_IID_ISpGramCompBackend"
    },
    {
      "offset": 11478,
      "name": "_IID_ISpGramCompBackendPrivate"
    },
    {
      "offset": 11478,
      "name": "_IID_ISpGrammarBuilder"
    },
    {
      "offset": 11478,
      "name": "_IID_ISpGrammarBuilder2"
    },
    {
      "offset": 11478,
      "name": "_IID_ISpGrammarBuilderPrivate"
    },
    {
      "offset": 11478,
      "name": "_IID_ISpGrammarCompiler"
    },
    {
      "offset": 11478,
      "name": "_IID_ISpGrammarInfo"
    },
    {
      "offset": 11478,
      "name": "_IID_ISpGrammarReferences"
    },
    {
      "offset": 11478,
      "name": "_IID_ISpITNProcessor"
    },
    {
      "offset": 11478,
      "name": "_IID_ISpLexicon"
    },
    {
      "offset": 11478,
      "name": "_IID_ISpMMSysAudio"
    },
    {
      "offset": 11478,
      "name": "_IID_ISpMMSysAudioConfig"
    },
    {
      "offset": 11478,
      "name": "_IID_ISpNotifySink"
    },
    {
      "offset": 11478,
      "name": "_IID_ISpNotifySource"
    },
    {
      "offset": 11478,
      "name": "_IID_ISpNotifyTranslator"
    },
    {
      "offset": 11478,
      "name": "_IID_ISpObjectToken"
    },
    {
      "offset": 11478,
      "name": "_IID_ISpObjectTokenCategory"
    },
    {
      "offset": 11478,
      "name": "_IID_ISpObjectTokenEnumBuilder"
    },
    {
      "offset": 11478,
      "name": "_IID_ISpObjectTokenInit"
    },
    {
      "offset": 11478,
      "name": "_IID_ISpObjectWithToken"
    },
    {
      "offset": 11478,
      "name": "_IID_ISpPhoneConverter"
    },
    {
      "offset": 11478,
      "name": "_IID_ISpPhoneticAlphabetConverter"
    },
    {
      "offset": 11478,
      "name": "_IID_ISpPhoneticAlphabetSelection"
    },
    {
      "offset": 11478,
      "name": "_IID_ISpPhrase"
    },
    {
      "offset": 11478,
      "name": "_IID_ISpPhrase2"
    },
    {
      "offset": 11478,
      "name": "_IID_ISpPhraseAlt"
    },
    {
      "offset": 11478,
      "name": "_IID_ISpPhraseBuilder"
    },
    {
      "offset": 11478,
      "name": "_IID_ISpPrivateEngineCallEx"
    },
    {
      "offset": 11478,
      "name": "_IID_ISpPromptEngineEx"
    },
    {
      "offset": 11478,
      "name": "_IID_ISpProperties"
    },
    {
      "offset": 11478,
      "name": "_IID_ISpRecoCategory"
    },
    {
      "offset": 11478,
      "name": "_IID_ISpRecoContext"
    },
    {
      "offset": 11478,
      "name": "_IID_ISpRecoContext2"
    },
    {
      "offset": 11478,
      "name": "_IID_ISpRecoGrammar"
    },
    {
      "offset": 11478,
      "name": "_IID_ISpRecoGrammar2"
    },
    {
      "offset": 11478,
      "name": "_IID_ISpRecoGrammarPrivate"
    },
    {
      "offset": 11478,
      "name": "_IID_ISpRecoResult"
    },
    {
      "offset": 11478,
      "name": "_IID_ISpRecoResult2"
    },
    {
      "offset": 11478,
      "name": "_IID_ISpRecognizer"
    },
    {
      "offset": 11478,
      "name": "_IID_ISpRecognizer2"
    },
    {
      "offset": 11478,
      "name": "_IID_ISpRecognizer3"
    },
    {
      "offset": 11478,
      "name": "_IID_ISpRecognizerPrivate"
    },
    {
      "offset": 11478,
      "name": "_IID_ISpRegDataKey"
    },
    {
      "offset": 11478,
      "name": "_IID_ISpResourceManager"
    },
    {
      "offset": 11478,
      "name": "_IID_ISpSRAlternates"
    },
    {
      "offset": 11478,
      "name": "_IID_ISpSRAlternates2"
    },
    {
      "offset": 11478,
      "name": "_IID_ISpSREngine"
    },
    {
      "offset": 11478,
      "name": "_IID_ISpSREngine2"
    },
    {
      "offset": 11478,
      "name": "_IID_ISpSREngineCFGParser"
    },
    {
      "offset": 11478,
      "name": "_IID_ISpSREngineGrammar"
    },
    {
      "offset": 11478,
      "name": "_IID_ISpSREngineSite"
    },
    {
      "offset": 11478,
      "name": "_IID_ISpSREngineSite2"
    },
    {
      "offset": 11478,
      "name": "_IID_ISpSREngineSitePriv"
    },
    {
      "offset": 11478,
      "name": "_IID_ISpSapiServer"
    },
    {
      "offset": 11478,
      "name": "_IID_ISpSerializeState"
    },
    {
      "offset": 11478,
      "name": "_IID_ISpShortcut"
    },
    {
      "offset": 11478,
      "name": "_IID_ISpStream"
    },
    {
      "offset": 11478,
      "name": "_IID_ISpStreamAccess"
    },
    {
      "offset": 11478,
      "name": "_IID_ISpStreamFormat"
    },
    {
      "offset": 11478,
      "name": "_IID_ISpStreamFormatConverter"
    },
    {
      "offset": 11478,
      "name": "_IID_ISpTTSEngine"
    },
    {
      "offset": 11478,
      "name": "_IID_ISpTTSEngineSSML"
    },
    {
      "offset": 11478,
      "name": "_IID_ISpTTSEngineSite"
    },
    {
      "offset": 11478,
      "name": "_IID_ISpTTSEngineSiteEx"
    },
    {
      "offset": 11478,
      "name": "_IID_ISpTaskManager"
    },
    {
      "offset": 11478,
      "name": "_IID_ISpThreadControl"
    },
    {
      "offset": 11478,
      "name": "_IID_ISpTokenUI"
    },
    {
      "offset": 11478,
      "name": "_IID_ISpTranscript"
    },
    {
      "offset": 11478,
      "name": "_IID_ISpTtsFormatConverter"
    },
    {
      "offset": 11478,
      "name": "_IID_ISpUXController"
    },
    {
      "offset": 11478,
      "name": "_IID_ISpUXHost"
    },
    {
      "offset": 11478,
      "name": "_IID_ISpUXPlugin"
    },
    {
      "offset": 11478,
      "name": "_IID_ISpVoice"
    },
    {
      "offset": 11478,
      "name": "_IID_ISpVoiceEx"
    },
    {
      "offset": 11478,
      "name": "_IID_ISpW3CSemanticInterpretation"
    },
    {
      "offset": 11478,
      "name": "_IID_ISpXMLRecoResult"
    },
    {
      "offset": 11478,
      "name": "_IID_ISpeechAudio"
    },
    {
      "offset": 11478,
      "name": "_IID_ISpeechAudioBufferInfo"
    },
    {
      "offset": 11478,
      "name": "_IID_ISpeechAudioFormat"
    },
    {
      "offset": 11478,
      "name": "_IID_ISpeechAudioStatus"
    },
    {
      "offset": 11478,
      "name": "_IID_ISpeechBaseStream"
    },
    {
      "offset": 11478,
      "name": "_IID_ISpeechCustomStream"
    },
    {
      "offset": 11478,
      "name": "_IID_ISpeechDataKey"
    },
    {
      "offset": 11478,
      "name": "_IID_ISpeechFileStream"
    },
    {
      "offset": 11478,
      "name": "_IID_ISpeechGrammarRule"
    },
    {
      "offset": 11478,
      "name": "_IID_ISpeechGrammarRuleState"
    },
    {
      "offset": 11478,
      "name": "_IID_ISpeechGrammarRuleStateTransition"
    },
    {
      "offset": 11478,
      "name": "_IID_ISpeechGrammarRuleStateTransitions"
    },
    {
      "offset": 11478,
      "name": "_IID_ISpeechGrammarRules"
    },
    {
      "offset": 11478,
      "name": "_IID_ISpeechLexicon"
    },
    {
      "offset": 11478,
      "name": "_IID_ISpeechLexiconPronunciation"
    },
    {
      "offset": 11478,
      "name": "_IID_ISpeechLexiconPronunciations"
    },
    {
      "offset": 11478,
      "name": "_IID_ISpeechLexiconWord"
    },
    {
      "offset": 11478,
      "name": "_IID_ISpeechLexiconWords"
    },
    {
      "offset": 11478,
      "name": "_IID_ISpeechMMSysAudio"
    },
    {
      "offset": 11478,
      "name": "_IID_ISpeechMemoryStream"
    },
    {
      "offset": 11478,
      "name": "_IID_ISpeechObjectToken"
    },
    {
      "offset": 11478,
      "name": "_IID_ISpeechObjectTokenCategory"
    },
    {
      "offset": 11478,
      "name": "_IID_ISpeechObjectTokens"
    },
    {
      "offset": 11478,
      "name": "_IID_ISpeechPhoneConverter"
    },
    {
      "offset": 11478,
      "name": "_IID_ISpeechPhraseAlternate"
    },
    {
      "offset": 11478,
      "name": "_IID_ISpeechPhraseAlternates"
    },
    {
      "offset": 11478,
      "name": "_IID_ISpeechPhraseElement"
    },
    {
      "offset": 11478,
      "name": "_IID_ISpeechPhraseElements"
    },
    {
      "offset": 11478,
      "name": "_IID_ISpeechPhraseInfo"
    },
    {
      "offset": 11478,
      "name": "_IID_ISpeechPhraseInfoBuilder"
    },
    {
      "offset": 11478,
      "name": "_IID_ISpeechPhraseProperties"
    },
    {
      "offset": 11478,
      "name": "_IID_ISpeechPhraseProperty"
    },
    {
      "offset": 11478,
      "name": "_IID_ISpeechPhraseReplacement"
    },
    {
      "offset": 11478,
      "name": "_IID_ISpeechPhraseReplacements"
    },
    {
      "offset": 11478,
      "name": "_IID_ISpeechPhraseRule"
    },
    {
      "offset": 11478,
      "name": "_IID_ISpeechPhraseRules"
    },
    {
      "offset": 11478,
      "name": "_IID_ISpeechRecoContext"
    },
    {
      "offset": 11478,
      "name": "_IID_ISpeechRecoGrammar"
    },
    {
      "offset": 11478,
      "name": "_IID_ISpeechRecoResult"
    },
    {
      "offset": 11478,
      "name": "_IID_ISpeechRecoResult2"
    },
    {
      "offset": 11478,
      "name": "_IID_ISpeechRecoResultDispatch"
    },
    {
      "offset": 11478,
      "name": "_IID_ISpeechRecoResultTimes"
    },
    {
      "offset": 11478,
      "name": "_IID_ISpeechRecognizer"
    },
    {
      "offset": 11478,
      "name": "_IID_ISpeechRecognizerStatus"
    },
    {
      "offset": 11478,
      "name": "_IID_ISpeechResourceLoader"
    },
    {
      "offset": 11478,
      "name": "_IID_ISpeechTextSelectionInformation"
    },
    {
      "offset": 11478,
      "name": "_IID_ISpeechVoice"
    },
    {
      "offset": 11478,
      "name": "_IID_ISpeechVoiceStatus"
    },
    {
      "offset": 11478,
      "name": "_IID_ISpeechWaveFormatEx"
    },
    {
      "offset": 11478,
      "name": "_IID_ISpeechXMLRecoResult"
    },
    {
      "offset": 11478,
      "name": "_IID__ISpCFGPhraseBuilder"
    },
    {
      "offset": 11478,
      "name": "_IID__ISpPhraseBuilder"
    },
    {
      "offset": 11478,
      "name": "_IID__ISpPrivateEngineCall"
    },
    {
      "offset": 11478,
      "name": "_IID__ISpRecoMaster"
    },
    {
      "offset": 11478,
      "name": "_IID__ISpSMLBuilder"
    },
    {
      "offset": 11478,
      "name": "_LIBID_SpeechDDKLib"
    },
    {
      "offset": 11478,
      "name": "_LIBID_SpeechInternalLib"
    },
    {
      "offset": 11478,
      "name": "_LIBID_SpeechLib"
    },
    {
      "offset": 11478,
      "name": "_LIBID_SpeechPrivateLib"
    },
    {
      "offset": 11478,
      "name": "_SPDFID_Text"
    },
    {
      "offset": 11478,
      "name": "_SPDFID_WaveFormatEx"
    },
    {
      "offset": 11478,
      "name": "_SPGDF_ContextFree"
    }
  ],
  "libSymbols": []
}