{
  "dllExports": [],
  "libExports": [
    {
      "name": "_GetFileVersionInfoA@16"
    },
    {
      "name": "_GetFileVersionInfoExW@20"
    },
    {
      "name": "_GetFileVersionInfoSizeA@8"
    },
    {
      "name": "_GetFileVersionInfoSizeExW@12"
    },
    {
      "name": "_GetFileVersionInfoSizeW@8"
    },
    {
      "name": "_GetFileVersionInfoW@16"
    },
    {
      "name": "_VerFindFileA@32"
    },
    {
      "name": "_VerFindFileW@32"
    },
    {
      "name": "_VerInstallFileA@32"
    },
    {
      "name": "_VerInstallFileW@32"
    },
    {
      "name": "_VerQueryValueA@16"
    },
    {
      "name": "_VerQueryValueW@16"
    }
  ],
  "libPublicSymbols": [
    {
      "offset": 1742,
      "name": "__IMPORT_DESCRIPTOR_VERSION"
    },
    {
      "offset": 2296,
      "name": "__NULL_IMPORT_DESCRIPTOR"
    },
    {
      "offset": 2606,
      "name": "VERSION_NULL_THUNK_DATA"
    },
    {
      "offset": 3178,
      "name": "_GetFileVersionInfoSizeA@8"
    },
    {
      "offset": 3178,
      "name": "__imp__GetFileVersionInfoSizeA@8"
    },
    {
      "offset": 2944,
      "name": "_GetFileVersionInfoA@16"
    },
    {
      "offset": 2944,
      "name": "__imp__GetFileVersionInfoA@16"
    },
    {
      "offset": 3656,
      "name": "_VerFindFileA@32"
    },
    {
      "offset": 3656,
      "name": "__imp__VerFindFileA@32"
    },
    {
      "offset": 3876,
      "name": "_VerInstallFileA@32"
    },
    {
      "offset": 3876,
      "name": "__imp__VerInstallFileA@32"
    },
    {
      "offset": 4100,
      "name": "_VerQueryValueA@16"
    },
    {
      "offset": 4100,
      "name": "__imp__VerQueryValueA@16"
    },
    {
      "offset": 3420,
      "name": "_GetFileVersionInfoSizeW@8"
    },
    {
      "offset": 3420,
      "name": "__imp__GetFileVersionInfoSizeW@8"
    },
    {
      "offset": 3540,
      "name": "_GetFileVersionInfoW@16"
    },
    {
      "offset": 3540,
      "name": "__imp__GetFileVersionInfoW@16"
    },
    {
      "offset": 3298,
      "name": "_GetFileVersionInfoSizeExW@12"
    },
    {
      "offset": 3298,
      "name": "__imp__GetFileVersionInfoSizeExW@12"
    },
    {
      "offset": 3060,
      "name": "_GetFileVersionInfoExW@20"
    },
    {
      "offset": 3060,
      "name": "__imp__GetFileVersionInfoExW@20"
    },
    {
      "offset": 3766,
      "name": "_VerFindFileW@32"
    },
    {
      "offset": 3766,
      "name": "__imp__VerFindFileW@32"
    },
    {
      "offset": 3988,
      "name": "_VerInstallFileW@32"
    },
    {
      "offset": 3988,
      "name": "__imp__VerInstallFileW@32"
    },
    {
      "offset": 4212,
      "name": "_VerQueryValueW@16"
    },
    {
      "offset": 4212,
      "name": "__imp__VerQueryValueW@16"
    }
  ],
  "libSymbols": [
    {
      "offset": 2944,
      "version": 0,
      "machine": 332,
      "timeDateStamp": 3620626155,
      "sizeOfData": 36,
      "dllName": "VERSION.dll",
      "symbolName": "_GetFileVersionInfoA@16",
      "type": "code",
      "nameType": "undecorate",
      "hint": 0,
      "name": "GetFileVersionInfoA"
    },
    {
      "offset": 3060,
      "version": 0,
      "machine": 332,
      "timeDateStamp": 4283885497,
      "sizeOfData": 38,
      "dllName": "VERSION.dll",
      "symbolName": "_GetFileVersionInfoExW@20",
      "type": "code",
      "nameType": "undecorate",
      "hint": 3,
      "name": "GetFileVersionInfoExW"
    },
    {
      "offset": 3178,
      "version": 0,
      "machine": 332,
      "timeDateStamp": 3619563014,
      "sizeOfData": 39,
      "dllName": "VERSION.dll",
      "symbolName": "_GetFileVersionInfoSizeA@8",
      "type": "code",
      "nameType": "undecorate",
      "hint": 4,
      "name": "GetFileVersionInfoSizeA"
    },
    {
      "offset": 3298,
      "version": 0,
      "machine": 332,
      "timeDateStamp": 4258627674,
      "sizeOfData": 42,
      "dllName": "VERSION.dll",
      "symbolName": "_GetFileVersionInfoSizeExW@12",
      "type": "code",
      "nameType": "undecorate",
      "hint": 6,
      "name": "GetFileVersionInfoSizeExW"
    },
    {
      "offset": 3420,
      "version": 0,
      "machine": 332,
      "timeDateStamp": 3379120665,
      "sizeOfData": 39,
      "dllName": "VERSION.dll",
      "symbolName": "_GetFileVersionInfoSizeW@8",
      "type": "code",
      "nameType": "undecorate",
      "hint": 7,
      "name": "GetFileVersionInfoSizeW"
    },
    {
      "offset": 3540,
      "version": 0,
      "machine": 332,
      "timeDateStamp": 4268567240,
      "sizeOfData": 36,
      "dllName": "VERSION.dll",
      "symbolName": "_GetFileVersionInfoW@16",
      "type": "code",
      "nameType": "undecorate",
      "hint": 8,
      "name": "GetFileVersionInfoW"
    },
    {
      "offset": 3656,
      "version": 0,
      "machine": 332,
      "timeDateStamp": 3556782347,
      "sizeOfData": 29,
      "dllName": "VERSION.dll",
      "symbolName": "_VerFindFileA@32",
      "type": "code",
      "nameType": "undecorate",
      "hint": 9,
      "name": "VerFindFileA"
    },
    {
      "offset": 3766,
      "version": 0,
      "machine": 332,
      "timeDateStamp": 4039779148,
      "sizeOfData": 29,
      "dllName": "VERSION.dll",
      "symbolName": "_VerFindFileW@32",
      "type": "code",
      "nameType": "undecorate",
      "hint": 10,
      "name": "VerFindFileW"
    },
    {
      "offset": 3876,
      "version": 0,
      "machine": 332,
      "timeDateStamp": 4051672993,
      "sizeOfData": 32,
      "dllName": "VERSION.dll",
      "symbolName": "_VerInstallFileA@32",
      "type": "code",
      "nameType": "undecorate",
      "hint": 11,
      "name": "VerInstallFileA"
    },
    {
      "offset": 3988,
      "version": 0,
      "machine": 332,
      "timeDateStamp": 3724523161,
      "sizeOfData": 32,
      "dllName": "VERSION.dll",
      "symbolName": "_VerInstallFileW@32",
      "type": "code",
      "nameType": "undecorate",
      "hint": 12,
      "name": "VerInstallFileW"
    },
    {
      "offset": 4100,
      "version": 0,
      "machine": 332,
      "timeDateStamp": 3596409967,
      "sizeOfData": 31,
      "dllName": "VERSION.dll",
      "symbolName": "_VerQueryValueA@16",
      "type": "code",
      "nameType": "undecorate",
      "hint": 15,
      "name": "VerQueryValueA"
    },
    {
      "offset": 4212,
      "version": 0,
      "machine": 332,
      "timeDateStamp": 4219238543,
      "sizeOfData": 31,
      "dllName": "VERSION.dll",
      "symbolName": "_VerQueryValueW@16",
      "type": "code",
      "nameType": "undecorate",
      "hint": 16,
      "name": "VerQueryValueW"
    }
  ]
}