{
  "dllExports": [],
  "libExports": [
    {
      "name": "_CreateAudioReverb",
      "ordinal": 2
    },
    {
      "name": "_CreateAudioReverb@4",
      "ordinal": 9
    },
    {
      "name": "_CreateAudioVolumeMeter",
      "ordinal": 3
    },
    {
      "name": "_CreateAudioVolumeMeter@4",
      "ordinal": 10
    },
    {
      "name": "_CreateFX",
      "ordinal": 4
    },
    {
      "name": "_X3DAudioCalculate",
      "ordinal": 5
    },
    {
      "name": "_X3DAudioInitialize",
      "ordinal": 6
    },
    {
      "name": "_XAudio2Create",
      "ordinal": 1
    },
    {
      "name": "_XAudio2Create@12",
      "ordinal": 8
    },
    {
      "name": "_XAudio2CreateWithVersionInfo",
      "ordinal": 7
    },
    {
      "name": "_XAudio2CreateWithVersionInfo@16",
      "ordinal": 11
    }
  ],
  "libPublicSymbols": [
    {
      "offset": 1582,
      "name": "__IMPORT_DESCRIPTOR_XAudio2_8"
    },
    {
      "offset": 2144,
      "name": "__NULL_IMPORT_DESCRIPTOR"
    },
    {
      "offset": 2456,
      "name": "XAudio2_8_NULL_THUNK_DATA"
    },
    {
      "offset": 3598,
      "name": "_XAudio2Create"
    },
    {
      "offset": 3598,
      "name": "__imp__XAudio2Create"
    },
    {
      "offset": 2798,
      "name": "_CreateAudioReverb"
    },
    {
      "offset": 2798,
      "name": "__imp__CreateAudioReverb"
    },
    {
      "offset": 3028,
      "name": "_CreateAudioVolumeMeter"
    },
    {
      "offset": 3028,
      "name": "__imp__CreateAudioVolumeMeter"
    },
    {
      "offset": 3266,
      "name": "_CreateFX"
    },
    {
      "offset": 3266,
      "name": "__imp__CreateFX"
    },
    {
      "offset": 3370,
      "name": "_X3DAudioCalculate"
    },
    {
      "offset": 3370,
      "name": "__imp__X3DAudioCalculate"
    },
    {
      "offset": 3484,
      "name": "_X3DAudioInitialize"
    },
    {
      "offset": 3484,
      "name": "__imp__X3DAudioInitialize"
    },
    {
      "offset": 3820,
      "name": "_XAudio2CreateWithVersionInfo"
    },
    {
      "offset": 3820,
      "name": "__imp__XAudio2CreateWithVersionInfo"
    },
    {
      "offset": 3708,
      "name": "_XAudio2Create@12"
    },
    {
      "offset": 3708,
      "name": "__imp__XAudio2Create@12"
    },
    {
      "offset": 2912,
      "name": "_CreateAudioReverb@4"
    },
    {
      "offset": 2912,
      "name": "__imp__CreateAudioReverb@4"
    },
    {
      "offset": 3146,
      "name": "_CreateAudioVolumeMeter@4"
    },
    {
      "offset": 3146,
      "name": "__imp__CreateAudioVolumeMeter@4"
    },
    {
      "offset": 3944,
      "name": "_XAudio2CreateWithVersionInfo@16"
    },
    {
      "offset": 3944,
      "name": "__imp__XAudio2CreateWithVersionInfo@16"
    }
  ],
  "libSymbols": [
    {
      "offset": 2798,
      "version": 0,
      "machine": 332,
      "timeDateStamp": 3741958949,
      "sizeOfData": 33,
      "dllName": "XAudio2_8.dll",
      "symbolName": "_CreateAudioReverb",
      "type": "code",
      "nameType": "ordinal",
      "ordinal": 2
    },
    {
      "offset": 2912,
      "version": 0,
      "machine": 332,
      "timeDateStamp": 3429399270,
      "sizeOfData": 35,
      "dllName": "XAudio2_8.dll",
      "symbolName": "_CreateAudioReverb@4",
      "type": "code",
      "nameType": "ordinal",
      "ordinal": 9
    },
    {
      "offset": 3028,
      "version": 0,
      "machine": 332,
      "timeDateStamp": 3803214318,
      "sizeOfData": 38,
      "dllName": "XAudio2_8.dll",
      "symbolName": "_CreateAudioVolumeMeter",
      "type": "code",
      "nameType": "ordinal",
      "ordinal": 3
    },
    {
      "offset": 3146,
      "version": 0,
      "machine": 332,
      "timeDateStamp": 3661722139,
      "sizeOfData": 40,
      "dllName": "XAudio2_8.dll",
      "symbolName": "_CreateAudioVolumeMeter@4",
      "type": "code",
      "nameType": "ordinal",
      "ordinal": 10
    },
    {
      "offset": 3266,
      "version": 0,
      "machine": 332,
      "timeDateStamp": 3848714149,
      "sizeOfData": 24,
      "dllName": "XAudio2_8.dll",
      "symbolName": "_CreateFX",
      "type": "code",
      "nameType": "ordinal",
      "ordinal": 4
    },
    {
      "offset": 3370,
      "version": 0,
      "machine": 332,
      "timeDateStamp": 3223999311,
      "sizeOfData": 33,
      "dllName": "XAudio2_8.dll",
      "symbolName": "_X3DAudioCalculate",
      "type": "code",
      "nameType": "ordinal",
      "ordinal": 5
    },
    {
      "offset": 3484,
      "version": 0,
      "machine": 332,
      "timeDateStamp": 3488379993,
      "sizeOfData": 34,
      "dllName": "XAudio2_8.dll",
      "symbolName": "_X3DAudioInitialize",
      "type": "code",
      "nameType": "ordinal",
      "ordinal": 6
    },
    {
      "offset": 3598,
      "version": 0,
      "machine": 332,
      "timeDateStamp": 3680462283,
      "sizeOfData": 29,
      "dllName": "XAudio2_8.dll",
      "symbolName": "_XAudio2Create",
      "type": "code",
      "nameType": "ordinal",
      "ordinal": 1
    },
    {
      "offset": 3708,
      "version": 0,
      "machine": 332,
      "timeDateStamp": 4109875057,
      "sizeOfData": 32,
      "dllName": "XAudio2_8.dll",
      "symbolName": "_XAudio2Create@12",
      "type": "code",
      "nameType": "ordinal",
      "ordinal": 8
    },
    {
      "offset": 3820,
      "version": 0,
      "machine": 332,
      "timeDateStamp": 3232635031,
      "sizeOfData": 44,
      "dllName": "XAudio2_8.dll",
      "symbolName": "_XAudio2CreateWithVersionInfo",
      "type": "code",
      "nameType": "ordinal",
      "ordinal": 7
    },
    {
      "offset": 3944,
      "version": 0,
      "machine": 332,
      "timeDateStamp": 4162683834,
      "sizeOfData": 47,
      "dllName": "XAudio2_8.dll",
      "symbolName": "_XAudio2CreateWithVersionInfo@16",
      "type": "code",
      "nameType": "ordinal",
      "ordinal": 11
    }
  ]
}